aws_codeartifact_poetry/__init__.py
aws_codeartifact_poetry/aws/__init__.py
aws_codeartifact_poetry/aws/session.py
aws_codeartifact_poetry/cli.py
aws_codeartifact_poetry/commands/__init__.py
aws_codeartifact_poetry/commands/login.py
aws_codeartifact_poetry/helpers/__init__.py
aws_codeartifact_poetry/helpers/catch_exceptions.py
aws_codeartifact_poetry/helpers/cmd.py
aws_codeartifact_poetry/helpers/logging.py
aws_codeartifact_poetry/helpers/poetry.py
aws_codeartifact_poetry-1.5.0.dist-info/LICENSE
aws_codeartifact_poetry-1.5.0.dist-info/METADATA
aws_codeartifact_poetry-1.5.0.dist-info/WHEEL
aws_codeartifact_poetry-1.5.0.dist-info/entry_points.txt
aws_codeartifact_poetry-1.5.0.dist-info/RECORD
