Metadata-Version: 2.1
Name: aws-codeartifact-poetry
Version: 1.5.0
Summary: AWS CodeArtifact Poetry CLI
Home-page: https://github.com/lucasvieirasilva/aws-codeartifact-poetry
License: Proprietary
Keywords: AWS,CODEARTIFACT,POETRY
Author: Lucas Vieira
Author-email: lucas.vieira94@outlook.com
Maintainer: Lucas Vieira
Maintainer-email: lucas.vieira94@outlook.com
Requires-Python: >=3.8.1,<4
Classifier: Intended Audience :: Developers
Classifier: License :: Other/Proprietary License
Classifier: Programming Language :: Python :: 3
Classifier: Programming Language :: Python :: 3.9
Classifier: Programming Language :: Python :: 3.10
Classifier: Programming Language :: Python :: 3.11
Classifier: Programming Language :: Python :: 3.12
Classifier: Programming Language :: Python :: 3.13
Requires-Dist: boto3 (>=1.20,<2.0)
Requires-Dist: click (>=8.0.3,<9.0.0)
Requires-Dist: toml (>=0.10.2,<0.11.0)
Project-URL: Repository, https://github.com/lucasvieirasilva/aws-codeartifact-poetry
